opensesame_plugins/psychopy/__init__.py
opensesame_plugins/psychopy/psychopy_gratingstim/__init__.py
opensesame_plugins/psychopy/psychopy_gratingstim/locale/ar.qm
opensesame_plugins/psychopy/psychopy_gratingstim/locale/ar.ts
opensesame_plugins/psychopy/psychopy_gratingstim/locale/bn.qm
opensesame_plugins/psychopy/psychopy_gratingstim/locale/bn.ts
opensesame_plugins/psychopy/psychopy_gratingstim/locale/de.qm
opensesame_plugins/psychopy/psychopy_gratingstim/locale/de.ts
opensesame_plugins/psychopy/psychopy_gratingstim/locale/es.qm
opensesame_plugins/psychopy/psychopy_gratingstim/locale/es.ts
opensesame_plugins/psychopy/psychopy_gratingstim/locale/fr.qm
opensesame_plugins/psychopy/psychopy_gratingstim/locale/fr.ts
opensesame_plugins/psychopy/psychopy_gratingstim/locale/he.qm
opensesame_plugins/psychopy/psychopy_gratingstim/locale/he.ts
opensesame_plugins/psychopy/psychopy_gratingstim/locale/hi.qm
opensesame_plugins/psychopy/psychopy_gratingstim/locale/hi.ts
opensesame_plugins/psychopy/psychopy_gratingstim/locale/id.qm
opensesame_plugins/psychopy/psychopy_gratingstim/locale/id.ts
opensesame_plugins/psychopy/psychopy_gratingstim/locale/it.qm
opensesame_plugins/psychopy/psychopy_gratingstim/locale/it.ts
opensesame_plugins/psychopy/psychopy_gratingstim/locale/ja.qm
opensesame_plugins/psychopy/psychopy_gratingstim/locale/ja.ts
opensesame_plugins/psychopy/psychopy_gratingstim/locale/ko.qm
opensesame_plugins/psychopy/psychopy_gratingstim/locale/ko.ts
opensesame_plugins/psychopy/psychopy_gratingstim/locale/nl.qm
opensesame_plugins/psychopy/psychopy_gratingstim/locale/nl.ts
opensesame_plugins/psychopy/psychopy_gratingstim/locale/pt.qm
opensesame_plugins/psychopy/psychopy_gratingstim/locale/pt.ts
opensesame_plugins/psychopy/psychopy_gratingstim/locale/ru.qm
opensesame_plugins/psychopy/psychopy_gratingstim/locale/ru.ts
opensesame_plugins/psychopy/psychopy_gratingstim/locale/tr.qm
opensesame_plugins/psychopy/psychopy_gratingstim/locale/tr.ts
opensesame_plugin_psychopy-0.8.0.dist-info/METADATA
opensesame_plugin_psychopy-0.8.0.dist-info/WHEEL
opensesame_plugin_psychopy-0.8.0.dist-info/RECORD
