Metadata-Version: 2.1
Name: opensesame-plugin-psychopy
Version: 0.8.0
Summary: PsychoPy plugins for OpenSesame
Home-page: https://osdoc.cogsci.nl/
License: COPYING
Author: Sebastiaan Mathôt
Author-email: s.mathot@cogsci.nl
Requires-Python: >=3.7
Classifier: License :: Other/Proprietary License
Classifier: Programming Language :: Python :: 3
Classifier: Programming Language :: Python :: 3.7
Classifier: Programming Language :: Python :: 3.8
Classifier: Programming Language :: Python :: 3.9
Classifier: Programming Language :: Python :: 3.10
Classifier: Programming Language :: Python :: 3.11
Requires-Dist: opensesame-core (>3.99.99)
Project-URL: Repository, https://github.com/open-cogsci/opensesame-plugin-psychopy
